Metadata-Version: 1.0
Name: SDKeyLogger
Version: 0.1
Summary: Provides KeyBoard Key Capturing.
Home-page: https://github.com/MRSDPY/Key-Logger
Author: Dankhara Shubham
Author-email: shubham.dankhara.p@gmail.com
License: MIT
Platform: UNKNOWN
